changy/__init__.py
changy/cli/__init__.py
changy/cli/__main__.py
changy/cli/application.py
changy/cli/changelog.py
changy/cli/unreleased.py
changy/cli/version.py
changy/constants.py
changy/errors.py
changy/logic.py
changy/settings.py
changy/tests/__init__.py
changy/tests/test_logic.py
changy/utils.py
changy-0.4.3.dist-info/LICENSE
changy-0.4.3.dist-info/METADATA
changy-0.4.3.dist-info/WHEEL
changy-0.4.3.dist-info/entry_points.txt
changy-0.4.3.dist-info/RECORD
